{
    "fieldDirections": [],
    "groupBy": [
        {
            "fieldName": "fruit",
            "groupOn" : "domain"
        }
    ],
    "closures": [],
    "attributeFields": [],
    "hideDisconnected": false,
    "hideDisconnectedBuiltIns": true,
    "sigColors": [
        {
            "sigName": "Banana",
            "color": "#FDDA0D"
        },
        {
            "sigName": "Apple",
            "color": "red"
        },
        {
            "sigName": "Pear",
            "color": "green"
        },
        {
            "sigName": "Basket",
            "color": "grey"
        }
    ],
    "sigIcons" : [
        {
            "path": "https://www.iconpacks.net/icons/2/free-apple-icon-3155-thumb.png",
            "sigName": "Apple",
            "height" : 70,
            "width" : 70
        },
        {
            "path": "https://cdn.iconscout.com/icon/free/png-512/free-banana-icon-download-in-svg-png-gif-file-formats--fruit-food-plantains-healthy-fruity-pack-drink-icons-31180.png",
            "sigName": "Banana",
            "height" : 70,
            "width" : 70
        },
        {
            "path": "https://icons.veryicon.com/png/o/food--drinks/fruits-and-vegetables-1/pear-58.png",
            "sigName": "Pear",
            "height" : 70,
            "width" : 70
        }
    ]
}